django_measurement/__init__.py
django_measurement/conf.py
django_measurement/forms.py
django_measurement/models.py
django_measurement/utils.py
django_measurement-3.2.4.dist-info/LICENSE
django_measurement-3.2.4.dist-info/METADATA
django_measurement-3.2.4.dist-info/WHEEL
django_measurement-3.2.4.dist-info/top_level.txt
django_measurement-3.2.4.dist-info/RECORD
